mmoney_cli/__init__.py
mmoney_cli/cli.py
mmoney_cli-0.1.0.dist-info/licenses/LICENSE
tests/__init__.py
tests/conftest.py
tests/test_cli.py
tests/test_cli_errors.py
mmoney_cli-0.1.0.dist-info/METADATA
mmoney_cli-0.1.0.dist-info/WHEEL
mmoney_cli-0.1.0.dist-info/entry_points.txt
mmoney_cli-0.1.0.dist-info/top_level.txt
mmoney_cli-0.1.0.dist-info/RECORD
