Metadata-Version: 2.4
Name: mmoney-cli
Version: 0.1.0
Summary: CLI for Monarch Money - access your financial data from the command line
Author-email: Alec Fong <alecfong1@gmail.com>
License: MIT
Project-URL: Homepage, https://github.com/theFong/mmoney-cli
Project-URL: Repository, https://github.com/theFong/mmoney-cli
Project-URL: Issues, https://github.com/theFong/mmoney-cli/issues
Keywords: monarch money,cli,finance,personal finance,budgeting
Classifier: Development Status :: 4 - Beta
Classifier: Environment :: Console
Classifier: Intended Audience :: End Users/Desktop
Classifier: Intended Audience :: Developers
Classifier: License :: OSI Approved :: MIT License
Classifier: Operating System :: OS Independent
Classifier: Programming Language :: Python :: 3
Classifier: Programming Language :: Python :: 3.9
Classifier: Programming Language :: Python :: 3.10
Classifier: Programming Language :: Python :: 3.11
Classifier: Programming Language :: Python :: 3.12
Classifier: Topic :: Office/Business :: Financial
Requires-Python: >=3.9
License-File: LICENSE
Requires-Dist: monarchmoneycommunity>=1.1.0
Requires-Dist: click>=8.0.0
Requires-Dist: keyring>=24.0.0
Provides-Extra: dev
Requires-Dist: pytest>=7.0.0; extra == "dev"
Requires-Dist: black>=23.0.0; extra == "dev"
Requires-Dist: ruff>=0.8.0; extra == "dev"
Requires-Dist: vulture>=2.13; extra == "dev"
Requires-Dist: pre-commit>=4.0.0; extra == "dev"
Requires-Dist: detect-secrets>=1.5.0; extra == "dev"
Dynamic: license-file
